zakuro/__init__.py
zakuro/build
zakuro/config.yaml
zakuro/context.py
zakuro/functional.py
zakuro/pkg_info.py
zakuro/var.py
zakuro/version
zakuro/worker.py
zakuro/fs/__init__.py
zakuro/fs/functional.py
zakuro/hub/__init__.py
zakuro/hub/functional.py
zakuro/nn/__init__.py
zakuro/nn/functional.py
zakuro/parsers/__init__.py
zakuro/parsers/zakuro_config_loader.py
zakuro_ai-0.1.1.dist-info/METADATA
zakuro_ai-0.1.1.dist-info/WHEEL
zakuro_ai-0.1.1.dist-info/top_level.txt
zakuro_ai-0.1.1.dist-info/RECORD
