Metadata-Version: 2.1
Name: zakuro-ai
Version: 0.1.1
Summary: Zakuro, the community cloud based technology powered by AI.
Home-page: https://zakuro.ai
Author: ZakuroAI Team
Author-email: info@zakuro.ai
License: BSD-3
Keywords: fog computing,machine learning
Platform: linux_debian_10_x86_64
Classifier: Intended Audience :: Developers
Classifier: Intended Audience :: Education
Classifier: Intended Audience :: Science/Research
Classifier: License :: OSI Approved :: BSD License
Classifier: Topic :: Scientific/Engineering
Classifier: Topic :: Scientific/Engineering :: Mathematics
Classifier: Topic :: Scientific/Engineering :: Artificial Intelligence
Classifier: Topic :: Software Development
Classifier: Topic :: Software Development :: Libraries
Classifier: Topic :: Software Development :: Libraries :: Python Modules
Classifier: Programming Language :: Python :: 3
Requires-Python: >=3.8
Requires-Dist: torch
Requires-Dist: torchvision
Requires-Dist: numpy
Requires-Dist: tqdm
Requires-Dist: gnutools-python
Requires-Dist: requests
Requires-Dist: pyYaml
Requires-Dist: minio
Requires-Dist: miniofs
